LICENSE
MANIFEST.in
README.rst
development.ini
setup.py
narcissus/__init__.py
narcissus.app.egg-info/PKG-INFO
narcissus.app.egg-info/SOURCES.txt
narcissus.app.egg-info/dependency_links.txt
narcissus.app.egg-info/entry_points.txt
narcissus.app.egg-info/namespace_packages.txt
narcissus.app.egg-info/requires.txt
narcissus.app.egg-info/top_level.txt
narcissus/app/__init__.py
narcissus/app/routes.py
narcissus/app/widgets/__init__.py
narcissus/app/widgets/static/css/custom_polymap.css
narcissus/app/widgets/static/css/graph.css
narcissus/app/widgets/static/css/logs.css
narcissus/app/widgets/static/css/polyselect.css
narcissus/app/widgets/static/js/graph.js
narcissus/app/widgets/static/js/logs.js
narcissus/app/widgets/static/js/modal.js
narcissus/app/widgets/static/js/d3/d3.geom.min.js
narcissus/app/widgets/static/js/d3/d3.layout.min.js
narcissus/app/widgets/static/js/d3/d3.min.js
narcissus/app/widgets/templates/__init__.py
narcissus/app/widgets/templates/__init__.pyc
narcissus/app/widgets/templates/graph.mak
narcissus/app/widgets/templates/logs.mak
narcissus/app/widgets/templates/widget.mak